{
    "available_from": {
        "key": "available_from",
        "value": "Immediately"
    },
    "business_model": {
        "key": "business_model",
        "value": "dealer_stock",
        "code": "dealer_stock"
    },
    "carline": "31355",
    "cartype": {
        "code": "N",
        "value": "New vehicle"
    },
    "color": {
        "out": {
            "value": "Oyster Silver Metallic"
        }
    },
    "dateoffer": {
        "key": "dateoffer",
        "value": "2024-11-21T03:56:20Z"
    },
    "dateproduction": "2024-11-20T00:00:00Z",
    "deliveryInfo": {
        "code": "70",
        "value": "At retailer for immediate delivery"
    },
    "dynamicAttributes": {
        "key": "dynamicAttributes",
        "CAP_CODE": {
            "key": "CAP_CODE",
            "value": "VWPA15RLI5EPTA  8"
        }
    },
    "drive": {
        "key": "drive",
        "value": "Front-wheel drive"
    },
    "dwa": {
        "key": "dwa",
        "value": "0"
    },
    "eComLink": {
        "key": "eComLink",
        "vwukecom": {
            "key": "vwukecom"
        }
    },
    "exhaust": {
        "key": "exhaust",
        "value": "Euro 6e"
    },
    "gear": {
        "key": "gear",
        "value": "Automatic"
    },
    "initialreg": "without",
    "localCarTitle": {
        "key": "localCarTitle",
        "value": "Passat R-Line 1.5 eTSI 150PS 7-speed DSG"
    },
    "manuf": {
        "key": "manuf",
        "value": "Volkswagen"
    },
    "mbvManuf": {
        "key": "mbvManuf",
        "value": "VW PKW",
        "code": "V"
    },
    "model": {
        "key": "model",
        "value": "Volkswagen Passat",
        "mbv": {
            "code": "CJ55DZ",
            "extension": "PDD/W15/W16/YOS"
        }
    },
    "model_ktText": {
        "key": "model_ktText",
        "value": "Passat"
    },
    "model_ktKey": {
        "key": "model_ktKey",
        "value": "BQBG"
    },
    "basemodel_ktText": {
        "key": "basemodel_ktText",
        "value": "Passat"
    },
    "basemodel_ktKey": {
        "key": "basemodel_ktKey",
        "value": "BQVP"
    },
    "modelyear": {
        "key": "modelyear",
        "value": "2025"
    },
    "motor": {
        "key": "motor",
        "capacity": {
            "key": "capacity",
            "unit": "cm³",
            "value": "1,498"
        },
        "fuel": {
            "key": "fuel",
            "value": "Petrol"
        },
        "powerKw": {
            "key": "power.kw",
            "unit": "kW",
            "value": "110"
        }
    },
    "padtype": {
        "key": "padtype",
        "value": "Inserts of front and outer rear seats in 'Karoso' R-Line fabric"
    },
    "paymentOptions": [
        "CASH",
        "PCP"
    ],
    "preuse": {
        "key": "preuse",
        "value": "hidden"
    },
    "price": {
        "key": "price",
        "symbol": "£",
        "unit": "£",
        "value": "46,065",
        "text": "Price"
    },
    "prices": {
        "key": "prices",
        "sale": {
            "key": "sale",
            "symbol": "£",
            "unit": "GBP",
            "value": "46,065.00",
            "code": "sale",
            "text": " "
        }
    },
    "salesgroup": "34685",
    "show_price_list": {
        "key": "show_price_list",
        "value": "false"
    },
    "stockLinks": {
        "key": "stockLinks",
        "vwukgsl": {
            "key": "vwukgsl",
            "value": "https://www.volkswagen.co.uk/en/new/available-stock-locator/gsl-plp.html/__app/search/car/R0JSNzcwMTIwMzcwNTIzMjAyNA=.app"
        }
    },
    "subtitle": {
        "key": "subtitle",
        "value": "Passat R-Line 1.5 eTSI 150PS 7-speed DSG"
    },
    "title": "Volkswagen Passat R-Line",
    "tradeport": {
        "key": "tradeport",
        "value": "false"
    },
    "vin": "WVWZZZCJ3SD019675",
    "availableFrom": "Immediately",
    "buildMyDealLinks": {},
    "businessModel": "dealer_stock",
    "campaigns": [],
    "carid": "GBR7701203705232024",
    "carTypeLabel": "New vehicle",
    "dealer": {
        "chain": {
            "key": ""
        },
        "country": "GBR",
        "gvoStatus": "HS",
        "hid": "77012",
        "key": "GBR77012",
        "city": {
            "key": "city",
            "value": "Rutherglen"
        },
        "name": {
            "key": "name",
            "value": "Arnold Clark Volkswagen (Glasg ow East)"
        },
        "phone": {
            "key": "phone",
            "value": "0141 6484873"
        },
        "position": {
            "key": "position",
            "latitude": {
                "key": "latitude",
                "value": "55.83511"
            },
            "longitude": {
                "key": "longitude",
                "value": "-4.20763"
            }
        },
        "regionCode": {
            "key": "regionCode",
            "value": "2"
        },
        "street": {
            "key": "street",
            "value": "29 Dalmarnock Road"
        },
        "zip": {
            "key": "zip",
            "value": "G73 1AE"
        }
    },
    "hypermediadealerperson": [
        {
            "key": "15241",
            "dealerPerson": {
                "items": [
                    {
                        "key": "address",
                        "values": [
                            {
                                "key": "city",
                                "value": "Rutherglen"
                            },
                            {
                                "key": "street",
                                "value": "29 Dalmarnock Road"
                            },
                            {
                                "key": "zip",
                                "value": "G73 1AE"
                            }
                        ]
                    },
                    {
                        "key": "brand",
                        "value": "V"
                    },
                    {
                        "key": "name",
                        "values": [
                            {
                                "key": "last",
                                "value": "Arnold Clark Volkswagen (Glasg ow East)"
                            }
                        ]
                    },
                    {
                        "key": "phone",
                        "values": [
                            {
                                "key": "office",
                                "value": "0141 6484873"
                            }
                        ]
                    }
                ]
            }
        }
    ],
    "hypermediaFinancing": {
        "default": {
            "disclaimer.product": "With Solutions Personal Contract Plan. 18s+. Subject to status. Ordered by 04 May 2026 from participating Retailers. Indemnities may be required. Subject to changes in vehicle or equipment prices. Offer may be varied or withdrawn at any time. Freepost Volkswagen Financial Services.",
            "disclaimer.calculation": "*With Solutions PCP. Ordered by 04/05/2026. T&Cs apply. Indemnities may be required. VW Financial Services.",
            "Rate": "535.65",
            "Duration": "48",
            "Mileage": "10,000",
            "DownPayment": "6,909.75",
            "DEPCONT": "5,000.00",
            "TD": "11,909.75",
            "INV": "46,065.00",
            "GFV": "16,820.10",
            "OTPFEE": "10.00",
            "TAP": "53,915.40",
            "NetCreditAmount": "34,155.25",
            "XSM": "7.20",
            "APR": "7.9",
            "AER": "7.85"
        },
        "financing-request": {
            "data": "<Request Domain=\"VTP.GSL.VW.UK\" Name=\"Defaults\"><Product ID=\"1130919\"/><Vehicle Type=\"New\"><Brand>BQ</Brand><Year>2025</Year><PriceModel>46065.00</PriceModel><PriceTotal>46065.00</PriceTotal><AltKey>VWPA15RLI5EPTA  8</AltKey></Vehicle><Dealer><Country>GBR</Country><ID>77012</ID></Dealer></Request>"
        },
        "products_request": {
            "data": "<Request Domain=\"VTP.GSL.VW.UK\" Name=\"Products\"><Vehicle Type=\"New\"><Brand>BQ</Brand><Year>2025</Year><PriceModel>46065.00</PriceModel><PriceTotal>46065.00</PriceTotal><AltKey>VWPA15RLI5EPTA  8</AltKey></Vehicle><Dealer><Country>GBR</Country><ID>77012</ID></Dealer></Request>"
        }
    },
    "hypermediaTechData": {
        "EngineDataBusiness": {
            "consumption": {
                "name": "fuel consumption",
                "data": [
                    {
                        "key": "fuel",
                        "name": "Gas",
                        "values": [
                            {
                                "key": "WLTP",
                                "name": "WLTP",
                                "values": [
                                    {
                                        "key": "PETROL",
                                        "name": "petrol",
                                        "text": "Fuel consumption",
                                        "values": [
                                            {
                                                "key": "LOW",
                                                "name": "Low",
                                                "items": [
                                                    {
                                                        "key": "HIGHLIGHTING",
                                                        "value": "EXTENDED"
                                                    }
                                                ],
                                                "value": "37.6",
                                                "rawValue": 37.6,
                                                "unit": "mpg"
                                            },
                                            {
                                                "key": "MEDIUM",
                                                "name": "Medium",
                                                "items": [
                                                    {
                                                        "key": "HIGHLIGHTING",
                                                        "value": "EXTENDED"
                                                    }
                                                ],
                                                "value": "51.4",
                                                "rawValue": 51.4,
                                                "unit": "mpg"
                                            },
                                            {
                                                "key": "HIGH",
                                                "name": "High",
                                                "items": [
                                                    {
                                                        "key": "HIGHLIGHTING",
                                                        "value": "EXTENDED"
                                                    }
                                                ],
                                                "value": "58.5",
                                                "rawValue": 58.5,
                                                "unit": "mpg"
                                            },
                                            {
                                                "key": "EXTRA_HIGH",
                                                "name": "Extra High",
                                                "items": [
                                                    {
                                                        "key": "HIGHLIGHTING",
                                                        "value": "EXTENDED"
                                                    }
                                                ],
                                                "value": "49.1",
                                                "rawValue": 49.1,
                                                "unit": "mpg"
                                            },
                                            {
                                                "key": "COMBINED",
                                                "name": "Combined",
                                                "items": [
                                                    {
                                                        "key": "HIGHLIGHTING",
                                                        "value": "EXTENDED,RESULT,DETAIL"
                                                    }
                                                ],
                                                "value": "50.0",
                                                "rawValue": 50,
                                                "unit": "mpg"
                                            }
                                        ]
                                    }
                                ]
                            }
                        ]
                    }
                ]
            },
            "emission": {
                "name": "CO2-Emissions",
                "data": [
                    {
                        "key": "fuel",
                        "name": "Gas",
                        "values": [
                            {
                                "key": "WLTP",
                                "name": "WLTP",
                                "values": [
                                    {
                                        "key": "PETROL",
                                        "name": "petrol",
                                        "text": "CO₂-Emissions",
                                        "values": [
                                            {
                                                "key": "COMBINED",
                                                "name": "combined",
                                                "items": [
                                                    {
                                                        "key": "HIGHLIGHTING",
                                                        "value": "EXTENDED,RESULT,DETAIL"
                                                    }
                                                ],
                                                "value": "129.0",
                                                "rawValue": 129,
                                                "unit": "g/km"
                                            }
                                        ]
                                    }
                                ]
                            }
                        ]
                    }
                ]
            }
        },
        "NEDC": {},
        "WLTP": {
            "consumption": {
                "name": "Fuel consumption combined according to WLTP",
                "data": [
                    {
                        "key": "fuel",
                        "values": [
                            {
                                "key": "SUSTAINING_PETROL",
                                "items": [
                                    {
                                        "key": "energy_management",
                                        "value": "SUSTAINING"
                                    },
                                    {
                                        "key": "fuel",
                                        "value": "PETROL"
                                    }
                                ],
                                "values": [
                                    {
                                        "key": "COMBINED",
                                        "name": "Combined",
                                        "value": "50.0",
                                        "unit": "mpg"
                                    },
                                    {
                                        "key": "HIGH",
                                        "name": "High",
                                        "value": "58.5",
                                        "unit": "mpg"
                                    },
                                    {
                                        "key": "MEDIUM",
                                        "name": "Medium",
                                        "value": "51.4",
                                        "unit": "mpg"
                                    },
                                    {
                                        "key": "LOW",
                                        "name": "Low",
                                        "value": "37.6",
                                        "unit": "mpg"
                                    },
                                    {
                                        "key": "EXTRA_HIGH",
                                        "name": "Extra High",
                                        "value": "49.1",
                                        "unit": "mpg"
                                    }
                                ]
                            }
                        ]
                    }
                ]
            },
            "emission": {
                "name": "CO₂ emissions combined according to WLTP",
                "data": [
                    {
                        "key": "co2",
                        "values": [
                            {
                                "key": "SUSTAINING_PETROL",
                                "items": [
                                    {
                                        "key": "energy_management",
                                        "value": "SUSTAINING"
                                    },
                                    {
                                        "key": "fuel",
                                        "value": "PETROL"
                                    }
                                ],
                                "values": [
                                    {
                                        "key": "COMBINED",
                                        "name": "Combined",
                                        "value": "129.0",
                                        "unit": "g/km"
                                    },
                                    {
                                        "key": "HIGH",
                                        "name": "High",
                                        "value": "110.0",
                                        "unit": "g/km"
                                    },
                                    {
                                        "key": "MEDIUM",
                                        "name": "Medium",
                                        "value": "125.0",
                                        "unit": "g/km"
                                    },
                                    {
                                        "key": "LOW",
                                        "name": "Low",
                                        "value": "171.0",
                                        "unit": "g/km"
                                    },
                                    {
                                        "key": "EXTRA_HIGH",
                                        "name": "Extra High",
                                        "value": "131.0",
                                        "unit": "g/km"
                                    }
                                ]
                            }
                        ]
                    }
                ]
            },
            "wltp_data": {
                "data": [
                    {
                        "key": "data",
                        "values": [
                            {
                                "key": "wltp_data_WLTP_DATA",
                                "items": [
                                    {
                                        "key": "energy_management",
                                        "value": "wltp_data"
                                    },
                                    {
                                        "key": "fuel",
                                        "value": "WLTP_DATA"
                                    }
                                ],
                                "values": [
                                    {
                                        "key": "DRAG_COEFFICIENT",
                                        "value": "0.279"
                                    },
                                    {
                                        "key": "HIGH_TYPING",
                                        "value": "0.0"
                                    },
                                    {
                                        "key": "DRAG_COEFFICIENT_H",
                                        "value": "0.332"
                                    },
                                    {
                                        "key": "MASS_VEHICLE_REAR",
                                        "value": "664.298",
                                        "unit": "kg"
                                    },
                                    {
                                        "key": "FUEL_TYPES|0",
                                        "value": "PETROL"
                                    },
                                    {
                                        "key": "EU_LEER_MIN",
                                        "value": "1573.0",
                                        "unit": "kg"
                                    },
                                    {
                                        "key": "MASS_ACTUAL",
                                        "value": "1637.329",
                                        "unit": "kg"
                                    },
                                    {
                                        "key": "EU_LEER_MAX",
                                        "value": "1763.0",
                                        "unit": "kg"
                                    },
                                    {
                                        "key": "VEHICLE_CLASS",
                                        "value": "CLASS_3B"
                                    },
                                    {
                                        "key": "ENGINE_TYPE",
                                        "value": "NOVC_HEV"
                                    },
                                    {
                                        "key": "MASS_VEHICLE_FRONT",
                                        "value": "898.031",
                                        "unit": "kg"
                                    },
                                    {
                                        "key": "MASS_VEHICLE",
                                        "value": "1562.329",
                                        "unit": "kg"
                                    }
                                ]
                            }
                        ]
                    }
                ]
            }
        }
    },
    "images": [
        {
            "key": "front_right_false_",
            "href": "https://media.volkswagen.com/Vilma/V/CJ5/2025/Front_Right/c4e38bfaeec2b9cd1eef6c7345106e34c044a09e50e8dcb014dd2ea9c6e2c403.png?width=1920",
            "type": "render",
            "contenttype": "image/png",
            "srcSet": [
                "https://media.volkswagen.com/Vilma/V/CJ5/2025/Front_Right/c4e38bfaeec2b9cd1eef6c7345106e34c044a09e50e8dcb014dd2ea9c6e2c403.png?width=160 160w",
                "https://media.volkswagen.com/Vilma/V/CJ5/2025/Front_Right/c4e38bfaeec2b9cd1eef6c7345106e34c044a09e50e8dcb014dd2ea9c6e2c403.png?width=320 320w",
                "https://media.volkswagen.com/Vilma/V/CJ5/2025/Front_Right/c4e38bfaeec2b9cd1eef6c7345106e34c044a09e50e8dcb014dd2ea9c6e2c403.png?width=640 640w",
                "https://media.volkswagen.com/Vilma/V/CJ5/2025/Front_Right/c4e38bfaeec2b9cd1eef6c7345106e34c044a09e50e8dcb014dd2ea9c6e2c403.png?width=1280 1280w",
                "https://media.volkswagen.com/Vilma/V/CJ5/2025/Front_Right/c4e38bfaeec2b9cd1eef6c7345106e34c044a09e50e8dcb014dd2ea9c6e2c403.png?width=1920 1920w",
                "https://media.volkswagen.com/Vilma/V/CJ5/2025/Front_Right/c4e38bfaeec2b9cd1eef6c7345106e34c044a09e50e8dcb014dd2ea9c6e2c403.png?width=2560 2560w"
            ]
        },
        {
            "key": "cockpit_dashboard_driver_true_",
            "href": "https://media.volkswagen.com/Vilma/V/CJ5/2025/Interior_Cockpit_Dashboard_Driver/7d56e983a51fc2c8587b299b769be267da3ec75e90f98001ac3dd9ebfc3bb359.png?width=1920",
            "type": "render",
            "contenttype": "image/png",
            "srcSet": [
                "https://media.volkswagen.com/Vilma/V/CJ5/2025/Interior_Cockpit_Dashboard_Driver/7d56e983a51fc2c8587b299b769be267da3ec75e90f98001ac3dd9ebfc3bb359.png?width=160 160w",
                "https://media.volkswagen.com/Vilma/V/CJ5/2025/Interior_Cockpit_Dashboard_Driver/7d56e983a51fc2c8587b299b769be267da3ec75e90f98001ac3dd9ebfc3bb359.png?width=320 320w",
                "https://media.volkswagen.com/Vilma/V/CJ5/2025/Interior_Cockpit_Dashboard_Driver/7d56e983a51fc2c8587b299b769be267da3ec75e90f98001ac3dd9ebfc3bb359.png?width=640 640w",
                "https://media.volkswagen.com/Vilma/V/CJ5/2025/Interior_Cockpit_Dashboard_Driver/7d56e983a51fc2c8587b299b769be267da3ec75e90f98001ac3dd9ebfc3bb359.png?width=1280 1280w",
                "https://media.volkswagen.com/Vilma/V/CJ5/2025/Interior_Cockpit_Dashboard_Driver/7d56e983a51fc2c8587b299b769be267da3ec75e90f98001ac3dd9ebfc3bb359.png?width=1920 1920w",
                "https://media.volkswagen.com/Vilma/V/CJ5/2025/Interior_Cockpit_Dashboard_Driver/7d56e983a51fc2c8587b299b769be267da3ec75e90f98001ac3dd9ebfc3bb359.png?width=2560 2560w"
            ]
        },
        {
            "key": "back_left_false_",
            "href": "https://media.volkswagen.com/Vilma/V/CJ5/2025/Back_Left/b1978ca8308b62abdd0301145b711c74ee04bfaddaa54a4a077467f548d51f91.png?width=1920",
            "type": "render",
            "contenttype": "image/png",
            "srcSet": [
                "https://media.volkswagen.com/Vilma/V/CJ5/2025/Back_Left/b1978ca8308b62abdd0301145b711c74ee04bfaddaa54a4a077467f548d51f91.png?width=160 160w",
                "https://media.volkswagen.com/Vilma/V/CJ5/2025/Back_Left/b1978ca8308b62abdd0301145b711c74ee04bfaddaa54a4a077467f548d51f91.png?width=320 320w",
                "https://media.volkswagen.com/Vilma/V/CJ5/2025/Back_Left/b1978ca8308b62abdd0301145b711c74ee04bfaddaa54a4a077467f548d51f91.png?width=640 640w",
                "https://media.volkswagen.com/Vilma/V/CJ5/2025/Back_Left/b1978ca8308b62abdd0301145b711c74ee04bfaddaa54a4a077467f548d51f91.png?width=1280 1280w",
                "https://media.volkswagen.com/Vilma/V/CJ5/2025/Back_Left/b1978ca8308b62abdd0301145b711c74ee04bfaddaa54a4a077467f548d51f91.png?width=1920 1920w",
                "https://media.volkswagen.com/Vilma/V/CJ5/2025/Back_Left/b1978ca8308b62abdd0301145b711c74ee04bfaddaa54a4a077467f548d51f91.png?width=2560 2560w"
            ]
        },
        {
            "key": "front_center_false_",
            "href": "https://media.volkswagen.com/Vilma/V/CJ5/2025/Front_Center/ffde7ce1b8ca19f29fe805bab16934ef91a1efe885099011892a24ba633ef244.png?width=1920",
            "type": "render",
            "contenttype": "image/png",
            "srcSet": [
                "https://media.volkswagen.com/Vilma/V/CJ5/2025/Front_Center/ffde7ce1b8ca19f29fe805bab16934ef91a1efe885099011892a24ba633ef244.png?width=160 160w",
                "https://media.volkswagen.com/Vilma/V/CJ5/2025/Front_Center/ffde7ce1b8ca19f29fe805bab16934ef91a1efe885099011892a24ba633ef244.png?width=320 320w",
                "https://media.volkswagen.com/Vilma/V/CJ5/2025/Front_Center/ffde7ce1b8ca19f29fe805bab16934ef91a1efe885099011892a24ba633ef244.png?width=640 640w",
                "https://media.volkswagen.com/Vilma/V/CJ5/2025/Front_Center/ffde7ce1b8ca19f29fe805bab16934ef91a1efe885099011892a24ba633ef244.png?width=1280 1280w",
                "https://media.volkswagen.com/Vilma/V/CJ5/2025/Front_Center/ffde7ce1b8ca19f29fe805bab16934ef91a1efe885099011892a24ba633ef244.png?width=1920 1920w",
                "https://media.volkswagen.com/Vilma/V/CJ5/2025/Front_Center/ffde7ce1b8ca19f29fe805bab16934ef91a1efe885099011892a24ba633ef244.png?width=2560 2560w"
            ]
        },
        {
            "key": "side_left_false_",
            "href": "https://media.volkswagen.com/Vilma/V/CJ5/2025/Side_Left/9ddbc2bfe06f6142e20b082bd79bf9558f3e39bd85f389a2773df0e202a73a8e.png?width=1920",
            "type": "render",
            "contenttype": "image/png",
            "srcSet": [
                "https://media.volkswagen.com/Vilma/V/CJ5/2025/Side_Left/9ddbc2bfe06f6142e20b082bd79bf9558f3e39bd85f389a2773df0e202a73a8e.png?width=160 160w",
                "https://media.volkswagen.com/Vilma/V/CJ5/2025/Side_Left/9ddbc2bfe06f6142e20b082bd79bf9558f3e39bd85f389a2773df0e202a73a8e.png?width=320 320w",
                "https://media.volkswagen.com/Vilma/V/CJ5/2025/Side_Left/9ddbc2bfe06f6142e20b082bd79bf9558f3e39bd85f389a2773df0e202a73a8e.png?width=640 640w",
                "https://media.volkswagen.com/Vilma/V/CJ5/2025/Side_Left/9ddbc2bfe06f6142e20b082bd79bf9558f3e39bd85f389a2773df0e202a73a8e.png?width=1280 1280w",
                "https://media.volkswagen.com/Vilma/V/CJ5/2025/Side_Left/9ddbc2bfe06f6142e20b082bd79bf9558f3e39bd85f389a2773df0e202a73a8e.png?width=1920 1920w",
                "https://media.volkswagen.com/Vilma/V/CJ5/2025/Side_Left/9ddbc2bfe06f6142e20b082bd79bf9558f3e39bd85f389a2773df0e202a73a8e.png?width=2560 2560w"
            ]
        },
        {
            "key": "side_right_false_",
            "href": "https://media.volkswagen.com/Vilma/V/CJ5/2025/Side_Right/326442003618e90dd410252c1dacde7d585ffd00f4d293aa551cf0d369329578.png?width=1920",
            "type": "render",
            "contenttype": "image/png",
            "srcSet": [
                "https://media.volkswagen.com/Vilma/V/CJ5/2025/Side_Right/326442003618e90dd410252c1dacde7d585ffd00f4d293aa551cf0d369329578.png?width=160 160w",
                "https://media.volkswagen.com/Vilma/V/CJ5/2025/Side_Right/326442003618e90dd410252c1dacde7d585ffd00f4d293aa551cf0d369329578.png?width=320 320w",
                "https://media.volkswagen.com/Vilma/V/CJ5/2025/Side_Right/326442003618e90dd410252c1dacde7d585ffd00f4d293aa551cf0d369329578.png?width=640 640w",
                "https://media.volkswagen.com/Vilma/V/CJ5/2025/Side_Right/326442003618e90dd410252c1dacde7d585ffd00f4d293aa551cf0d369329578.png?width=1280 1280w",
                "https://media.volkswagen.com/Vilma/V/CJ5/2025/Side_Right/326442003618e90dd410252c1dacde7d585ffd00f4d293aa551cf0d369329578.png?width=1920 1920w",
                "https://media.volkswagen.com/Vilma/V/CJ5/2025/Side_Right/326442003618e90dd410252c1dacde7d585ffd00f4d293aa551cf0d369329578.png?width=2560 2560w"
            ]
        },
        {
            "key": "side__true_",
            "href": "https://media.volkswagen.com/Vilma/V/CJ5/2025/Interior_Side/1bdd918056a0f2a385a3b2727598dbe3ab2275bec14ed2f6df50655a1ebaae95.png?width=1920",
            "type": "render",
            "contenttype": "image/png",
            "srcSet": [
                "https://media.volkswagen.com/Vilma/V/CJ5/2025/Interior_Side/1bdd918056a0f2a385a3b2727598dbe3ab2275bec14ed2f6df50655a1ebaae95.png?width=160 160w",
                "https://media.volkswagen.com/Vilma/V/CJ5/2025/Interior_Side/1bdd918056a0f2a385a3b2727598dbe3ab2275bec14ed2f6df50655a1ebaae95.png?width=320 320w",
                "https://media.volkswagen.com/Vilma/V/CJ5/2025/Interior_Side/1bdd918056a0f2a385a3b2727598dbe3ab2275bec14ed2f6df50655a1ebaae95.png?width=640 640w",
                "https://media.volkswagen.com/Vilma/V/CJ5/2025/Interior_Side/1bdd918056a0f2a385a3b2727598dbe3ab2275bec14ed2f6df50655a1ebaae95.png?width=1280 1280w",
                "https://media.volkswagen.com/Vilma/V/CJ5/2025/Interior_Side/1bdd918056a0f2a385a3b2727598dbe3ab2275bec14ed2f6df50655a1ebaae95.png?width=1920 1920w",
                "https://media.volkswagen.com/Vilma/V/CJ5/2025/Interior_Side/1bdd918056a0f2a385a3b2727598dbe3ab2275bec14ed2f6df50655a1ebaae95.png?width=2560 2560w"
            ]
        },
        {
            "key": "back_right_false_",
            "href": "https://media.volkswagen.com/Vilma/V/CJ5/2025/Back_Right/1a6f6b23df268cc414ae39250b4c7e454c0b0255616b676cb751c9af9934f635.png?width=1920",
            "type": "render",
            "contenttype": "image/png",
            "srcSet": [
                "https://media.volkswagen.com/Vilma/V/CJ5/2025/Back_Right/1a6f6b23df268cc414ae39250b4c7e454c0b0255616b676cb751c9af9934f635.png?width=160 160w",
                "https://media.volkswagen.com/Vilma/V/CJ5/2025/Back_Right/1a6f6b23df268cc414ae39250b4c7e454c0b0255616b676cb751c9af9934f635.png?width=320 320w",
                "https://media.volkswagen.com/Vilma/V/CJ5/2025/Back_Right/1a6f6b23df268cc414ae39250b4c7e454c0b0255616b676cb751c9af9934f635.png?width=640 640w",
                "https://media.volkswagen.com/Vilma/V/CJ5/2025/Back_Right/1a6f6b23df268cc414ae39250b4c7e454c0b0255616b676cb751c9af9934f635.png?width=1280 1280w",
                "https://media.volkswagen.com/Vilma/V/CJ5/2025/Back_Right/1a6f6b23df268cc414ae39250b4c7e454c0b0255616b676cb751c9af9934f635.png?width=1920 1920w",
                "https://media.volkswagen.com/Vilma/V/CJ5/2025/Back_Right/1a6f6b23df268cc414ae39250b4c7e454c0b0255616b676cb751c9af9934f635.png?width=2560 2560w"
            ]
        },
        {
            "key": "front_left_false_",
            "href": "https://media.volkswagen.com/Vilma/V/CJ5/2025/Front_Left/1ad2680e1166a6034582c5e1c5126885a3dcac9b8d668a9bba08738c80ce2569.png?width=1920",
            "type": "render",
            "contenttype": "image/png",
            "srcSet": [
                "https://media.volkswagen.com/Vilma/V/CJ5/2025/Front_Left/1ad2680e1166a6034582c5e1c5126885a3dcac9b8d668a9bba08738c80ce2569.png?width=160 160w",
                "https://media.volkswagen.com/Vilma/V/CJ5/2025/Front_Left/1ad2680e1166a6034582c5e1c5126885a3dcac9b8d668a9bba08738c80ce2569.png?width=320 320w",
                "https://media.volkswagen.com/Vilma/V/CJ5/2025/Front_Left/1ad2680e1166a6034582c5e1c5126885a3dcac9b8d668a9bba08738c80ce2569.png?width=640 640w",
                "https://media.volkswagen.com/Vilma/V/CJ5/2025/Front_Left/1ad2680e1166a6034582c5e1c5126885a3dcac9b8d668a9bba08738c80ce2569.png?width=1280 1280w",
                "https://media.volkswagen.com/Vilma/V/CJ5/2025/Front_Left/1ad2680e1166a6034582c5e1c5126885a3dcac9b8d668a9bba08738c80ce2569.png?width=1920 1920w",
                "https://media.volkswagen.com/Vilma/V/CJ5/2025/Front_Left/1ad2680e1166a6034582c5e1c5126885a3dcac9b8d668a9bba08738c80ce2569.png?width=2560 2560w"
            ]
        }
    ],
    "isCarCommercial": false,
    "isDwa": false,
    "isLeasing": false,
    "isTradeport": false,
    "isVat": false,
    "key": "R0JSNzcwMTIwMzcwNTIzMjAyNA=",
    "noiseLevel": "63 dB(A)",
    "oneShopLink": "true",
    "parsedPrice": {
        "expenses": {},
        "label": "£ 46,065",
        "suffix": {
            "disclaimer": "Prices listed are Volkswagen UK’s recommended On The Road (OTR) retail price. Actual prices are set by Volkswagen authorised retailers in their sole discretion – always obtain these prices from your chosen Volkswagen Retailer. Your contract is always with the Volkswagen Retailer. Volkswagen UK’s recommended OTR includes: delivery charge, number plates, new vehicle registration fee, the first year's Vehicle Excise Duty and VAT (calculated at 20%).",
            "label": " "
        },
        "symbol": "£",
        "totalPrice": {},
        "unit": "GBP",
        "value": 46065,
        "valueString": "46,065"
    },
    "powerLabel": " 110 kW",
    "shouldFetchReserved": false,
    "webcalcOption": [],
    "equipmentTabs": [
        {
            "i18nKey": "detailPage.detailedSpecs.tab.overview.label",
            "items": [],
            "key": "overview"
        },
        {
            "i18nKey": "detailPage.detailedSpecs.tab.vehicleData.label",
            "items": [],
            "key": "vehicleData"
        },
        {
            "headline": "Standard equipment",
            "isStatic": false,
            "items": [
                {
                    "headline": "Interior equipment",
                    "key": "INTERIEUR",
                    "values": [
                        {
                            "details": "",
                            "disclaimers": [],
                            "text": "`Air Care Climatronic` (3-zone) with rear air conditioning control panel"
                        },
                        {
                            "details": "",
                            "disclaimers": [],
                            "text": "Dynamic road sign display"
                        },
                        {
                            "details": "",
                            "disclaimers": [],
                            "text": "Brushed stainless steel pedals"
                        },
                        {
                            "details": "",
                            "disclaimers": [],
                            "text": "Laminated safety glass for side windows , privacy glass in rear window and rear side windows"
                        },
                        {
                            "details": "",
                            "disclaimers": [],
                            "text": "Carpet mats, front and rear"
                        },
                        {
                            "details": "",
                            "disclaimers": [],
                            "text": "Net partition"
                        },
                        {
                            "details": "",
                            "disclaimers": [],
                            "text": "Luggage compartment floor including luggage management system with movable bar and belt"
                        },
                        {
                            "details": "",
                            "disclaimers": [],
                            "text": "Luggage compartment cover, power operated"
                        },
                        {
                            "details": "",
                            "disclaimers": [],
                            "text": "Sunblinds for rear side windows, manual"
                        },
                        {
                            "details": "",
                            "disclaimers": [],
                            "text": "Laminated safety glass windshield,with   heat and sound insulating"
                        },
                        {
                            "details": "",
                            "disclaimers": [],
                            "text": "Auto-dimming rear view mirror"
                        },
                        {
                            "details": "",
                            "disclaimers": [],
                            "text": "Aluminium decorative inserts"
                        },
                        {
                            "details": "",
                            "disclaimers": [],
                            "text": "Sun visors with illuminated vanity mirrors for driver and front passenger"
                        },
                        {
                            "details": "",
                            "disclaimers": [],
                            "text": "Black roof lining"
                        },
                        {
                            "details": "",
                            "disclaimers": [],
                            "text": "LED footwell illumination in front and rear"
                        },
                        {
                            "details": "",
                            "disclaimers": [],
                            "text": "Scuff plates in door apertures"
                        }
                    ]
                },
                {
                    "headline": "Exterior equipment",
                    "key": "EXTERIEUR",
                    "values": [
                        {
                            "details": "",
                            "disclaimers": [],
                            "text": "'R-Line' body-coloured bumpers"
                        },
                        {
                            "details": "",
                            "disclaimers": [],
                            "text": "Easy Open & Close - Electric tailgate with virtual pedal activation"
                        },
                        {
                            "details": "",
                            "disclaimers": [],
                            "text": "Exterior mirrors, convex on the left and aspherical on the right"
                        },
                        {
                            "details": "",
                            "disclaimers": [],
                            "text": "Body-coloured rear spoiler"
                        },
                        {
                            "details": "",
                            "disclaimers": [],
                            "text": "Electrically heated, adjustable and  folding door mirrors"
                        },
                        {
                            "details": "",
                            "disclaimers": [],
                            "text": "Park Assist with Park Distance Control"
                        },
                        {
                            "details": "",
                            "disclaimers": [],
                            "text": "IQ.LIGHT - LED Matrix headlamps with LED sep. daytime running light, dynamic cornering light and dynamic turn signal"
                        },
                        {
                            "details": "",
                            "disclaimers": [],
                            "text": "Rear wash/wipe with intermittent wipe"
                        },
                        {
                            "details": "",
                            "disclaimers": [],
                            "text": "LED rear combination lamp, variable lighting functions"
                        }
                    ]
                },
                {
                    "headline": "Wheels/tyres",
                    "key": "WHEELS",
                    "values": [
                        {
                            "details": "",
                            "disclaimers": [],
                            "text": "AirStop® tyres 235/45 R18, low rolling"
                        },
                        {
                            "details": "",
                            "disclaimers": [],
                            "text": "Tyre mobility kit including compressor and sealing foam. In lieu of spare wheel"
                        },
                        {
                            "details": "",
                            "disclaimers": [],
                            "text": "Alloy wheels 18\" 'Coventry', black diamond turned surface"
                        },
                        {
                            "details": "",
                            "disclaimers": [],
                            "text": "Tyre pressure loss indicator"
                        },
                        {
                            "text": "tyreLabelsLink"
                        }
                    ],
                    "i18nKey": "detailPage.detailedSpecs.tab.additionalEquipment.wheels.heading"
                },
                {
                    "headline": "Steering wheels",
                    "key": "STEERING",
                    "values": [
                        {
                            "details": "",
                            "disclaimers": [],
                            "text": "Leather-wrapped, heated, multi-function sports steering wheel with shift paddles"
                        }
                    ]
                },
                {
                    "headline": "Seats",
                    "key": "SEAT",
                    "values": [
                        {
                            "details": "",
                            "disclaimers": [],
                            "text": "Massage seats in front (13 points)"
                        },
                        {
                            "details": "",
                            "disclaimers": [],
                            "text": "Inserts of front and outer rear seats in 'Karoso' R-Line fabric"
                        },
                        {
                            "details": "",
                            "disclaimers": [],
                            "text": "Sports seats in front"
                        },
                        {
                            "details": "",
                            "disclaimers": [],
                            "text": "Manual height adjustment for front seats w/seat cushion tilt & depth adjustm. and electric backrest adjustm. on both sides"
                        },
                        {
                            "details": "",
                            "disclaimers": [],
                            "text": "Integrated head restraints for front seats"
                        },
                        {
                            "details": "",
                            "disclaimers": [],
                            "text": "Unsplit rear seat bench, split folding backrest with centre armrest"
                        },
                        {
                            "details": "",
                            "disclaimers": [],
                            "text": "Three rear head restraints"
                        },
                        {
                            "details": "",
                            "disclaimers": [],
                            "text": "Heated front seats"
                        },
                        {
                            "details": "",
                            "disclaimers": [],
                            "text": "Center armrest in rear"
                        },
                        {
                            "details": "",
                            "disclaimers": [],
                            "text": "Power-adjustable lumbar support in front seats  "
                        }
                    ]
                },
                {
                    "headline": "Infotainment",
                    "key": "INFOTAINMENT",
                    "values": [
                        {
                            "details": "",
                            "disclaimers": [],
                            "text": "e-Sim card for online connectivity"
                        },
                        {
                            "details": "",
                            "disclaimers": [],
                            "text": "IDA voice assistance with ChatGPT"
                        },
                        {
                            "details": "",
                            "disclaimers": [],
                            "text": "Digital radio reception (DAB)"
                        },
                        {
                            "details": "",
                            "disclaimers": [],
                            "text": "2 USB-C ports in the front, 2 USB-C charging sockets on the centre console in rear, charging capacity up to 45 W"
                        },
                        {
                            "details": "",
                            "disclaimers": [],
                            "text": "Digital Cockpit Pro 10.25\" high resolution"
                        },
                        {
                            "details": "",
                            "disclaimers": [],
                            "text": "Navigation system"
                        },
                        {
                            "details": "",
                            "disclaimers": [],
                            "text": "Infotainment system with 12.9\" display"
                        },
                        {
                            "details": "",
                            "disclaimers": [],
                            "text": "8 speakers"
                        },
                        {
                            "details": "",
                            "disclaimers": [],
                            "text": "Wireless App-Connect"
                        },
                        {
                            "details": "",
                            "disclaimers": [],
                            "text": "Inductive smartphone charging without external antenna connetction (fast charge)"
                        }
                    ]
                },
                {
                    "headline": "Technology and safety",
                    "key": "SAFETY",
                    "values": [
                        {
                            "details": "",
                            "disclaimers": [],
                            "text": "Advanced driver attention & drowsiness monitor"
                        },
                        {
                            "details": "",
                            "disclaimers": [],
                            "text": "Memory feature for Park Assist"
                        },
                        {
                            "details": "",
                            "disclaimers": [],
                            "text": "Front Cross Traffic Assist"
                        },
                        {
                            "details": "",
                            "disclaimers": [],
                            "text": "Rear-view camera"
                        },
                        {
                            "details": "",
                            "disclaimers": [],
                            "text": "Predictive speed limiter"
                        },
                        {
                            "details": "",
                            "disclaimers": [],
                            "text": "'e-call' Emergency call service"
                        },
                        {
                            "details": "",
                            "disclaimers": [],
                            "text": "Multifunction camera"
                        },
                        {
                            "details": "",
                            "disclaimers": [],
                            "text": "Interior Ambient lighting with 30 colour options"
                        },
                        {
                            "details": "",
                            "disclaimers": [],
                            "text": "Rear shock absorption for sports version"
                        },
                        {
                            "details": "",
                            "disclaimers": [],
                            "text": "Illuminated Lightline between headlamps and illuminated door handle recesses"
                        },
                        {
                            "details": "",
                            "disclaimers": [],
                            "text": "Hill start assist"
                        },
                        {
                            "details": "",
                            "disclaimers": [],
                            "text": "Electronic parking brake with auto-hold  function"
                        },
                        {
                            "details": "",
                            "disclaimers": [],
                            "text": "Predictive pedestrian protection"
                        },
                        {
                            "details": "",
                            "disclaimers": [],
                            "text": "ESC (Electronic Stability Control) with brake booster"
                        },
                        {
                            "details": "",
                            "disclaimers": [],
                            "text": "Welcome light with surround lighting"
                        },
                        {
                            "details": "",
                            "disclaimers": [],
                            "text": "Adaptive Chassis Control DCC Pro incl. Driving mode selection"
                        },
                        {
                            "details": "",
                            "disclaimers": [],
                            "text": "Isofix child seat preparation, easy-fit (for two outer rear seats, and front passenger seat), compatible with I-size"
                        },
                        {
                            "details": "",
                            "disclaimers": [],
                            "text": "Oncoming vehicle braking when turning including swerve support"
                        },
                        {
                            "details": "",
                            "disclaimers": [],
                            "text": "Manual child safety lock"
                        },
                        {
                            "details": "",
                            "disclaimers": [],
                            "text": "Keyless locking and starting system Keyless access with SAFELOCK"
                        },
                        {
                            "details": "",
                            "disclaimers": [],
                            "text": "Driver and front passenger airbag with front passenger airbag deactivation, including knee airbag on driver side"
                        },
                        {
                            "details": "",
                            "disclaimers": [],
                            "text": "Curtain and side airbags in front with centre airbag"
                        },
                        {
                            "details": "",
                            "disclaimers": [],
                            "text": "Travel Assist with Lane Assist"
                        },
                        {
                            "details": "",
                            "disclaimers": [],
                            "text": "With extended safety system (proactive passenger protection system)"
                        },
                        {
                            "details": "",
                            "disclaimers": [],
                            "text": "Lane change system Side Assist, Rear Traffic Alert and exit warning system"
                        },
                        {
                            "details": "",
                            "disclaimers": [],
                            "text": "Advanced high-beam control Dynamic Light Assist for LED matrix headlamps"
                        },
                        {
                            "details": "",
                            "disclaimers": [],
                            "text": "Front Assist - Autonomous emergency  braking with pedestrian and cyclist monitoring"
                        },
                        {
                            "details": "",
                            "disclaimers": [],
                            "text": "Rain sensor"
                        },
                        {
                            "details": "",
                            "disclaimers": [],
                            "text": "Dynamic headlight range control, with dynamic cornering light"
                        },
                        {
                            "details": "",
                            "disclaimers": [],
                            "text": "Rear fog lights and rear reversing lights on both sides"
                        },
                        {
                            "details": "",
                            "disclaimers": [],
                            "text": "Adaptive cruise control (ACC)"
                        },
                        {
                            "details": "",
                            "disclaimers": [],
                            "text": "Light mode for poor weather- rain, fog or snow"
                        },
                        {
                            "details": "",
                            "disclaimers": [],
                            "text": "Two-tone horn"
                        },
                        {
                            "details": "",
                            "disclaimers": [],
                            "text": "Automatic headlight control with LED separate daytime running light and coming home and leaving home feature"
                        },
                        {
                            "details": "",
                            "disclaimers": [],
                            "text": "Additional LED warning light (door area) in front and rear"
                        }
                    ]
                },
                {
                    "headline": "Engine/transmission",
                    "key": "ENGINE",
                    "values": [
                        {
                            "details": "",
                            "disclaimers": [],
                            "text": "Start-stop system with battery  regeneration (recuperation - energy recovery during braking)"
                        }
                    ]
                },
                {
                    "headline": "other",
                    "key": "OTHERS",
                    "values": [
                        {
                            "details": "",
                            "disclaimers": [],
                            "text": "Car2X - intelligent vehicle networking"
                        },
                        {
                            "details": "",
                            "disclaimers": [],
                            "text": "Dynamic Chassis Control (DCC), variable suspension settings, sport, comfort and normal"
                        },
                        {
                            "details": "",
                            "disclaimers": [],
                            "text": "NCAP pack inc. Pedestrian monitoring, lane assist, adaptive cruise control and autonomous emergency braking"
                        },
                        {
                            "details": "",
                            "disclaimers": [],
                            "text": "Black Styling pack"
                        },
                        {
                            "details": "",
                            "disclaimers": [],
                            "text": "Preparation for \"We Connect\" and \"We Connect Plus\""
                        }
                    ]
                }
            ],
            "key": "serie_equip"
        }
    ],
    "tyreLabels": [
        {
            "prNumber": "REIJ86",
            "labels": [
                {
                    "key": "584484",
                    "tyreLabelUrl": "https://eprel.ec.europa.eu/api/products/tyres/1451197/labels?noRedirect=false&format=SVG&supplier_label=false",
                    "productSheetUrl": "https://eprel.ec.europa.eu/api/products/tyres/1451197/fiches?noRedirect=false&language=EN",
                    "tradeName": "Goodyear",
                    "tyreTypeIdentifier": "584484",
                    "eprelUrl": "https://eprel.ec.europa.eu/qr/1451197",
                    "sizeDesignation_loadCapacityIndex": "94",
                    "sizeDesignation_speedCategorySymbol": "W",
                    "sizeDesignation_tyreSizeDesignation": "235/45 R18"
                },
                {
                    "key": "41128",
                    "tyreLabelUrl": "https://eprel.ec.europa.eu/api/products/tyres/1737090/labels?noRedirect=false&format=SVG&supplier_label=false",
                    "productSheetUrl": "https://eprel.ec.europa.eu/api/products/tyres/1737090/fiches?noRedirect=false&language=EN",
                    "tradeName": "Pirelli",
                    "tyreTypeIdentifier": "41128",
                    "eprelUrl": "https://eprel.ec.europa.eu/qr/1737090",
                    "sizeDesignation_loadCapacityIndex": "94",
                    "sizeDesignation_speedCategorySymbol": "W",
                    "sizeDesignation_tyreSizeDesignation": "235/45 R18"
                },
                {
                    "key": "24625",
                    "tyreLabelUrl": "https://eprel.ec.europa.eu/api/products/tyres/501891/labels?noRedirect=false&format=SVG&supplier_label=false",
                    "productSheetUrl": "https://eprel.ec.europa.eu/api/products/tyres/501891/fiches?noRedirect=false&language=EN",
                    "tradeName": "Bridgestone",
                    "tyreTypeIdentifier": "24625",
                    "eprelUrl": "https://eprel.ec.europa.eu/qr/501891",
                    "sizeDesignation_loadCapacityIndex": "94",
                    "sizeDesignation_speedCategorySymbol": "W",
                    "sizeDesignation_tyreSizeDesignation": "235/45 R18"
                }
            ]
        }
    ],
    "warranties": [],
    "contactData": {
        "contactPersonPhone": "0141 6484873",
        "dealerAddress": "G73 1AE Rutherglen",
        "dealerLabel": "Arnold Clark Volkswagen (Glasg ow East)",
        "dealerPhone": "0141 6484873",
        "dealerPosition": {
            "latitude": 55.83511,
            "longitude": -4.20763
        },
        "dealerStreet": "29 Dalmarnock Road",
        "dealerZipCode": "G73 1AE"
    }
}